degiro_cli-0.1.2.data/scripts/degiro-history
degiro_cli-0.1.2.data/scripts/degiro-login
degiro_cli-0.1.2.data/scripts/degiro-search
degirocli/__init__.py
degirocli/helpers.py
degirocli/history.py
degirocli/login.py
degirocli/search.py
degiro_cli-0.1.2.dist-info/LICENSE
degiro_cli-0.1.2.dist-info/METADATA
degiro_cli-0.1.2.dist-info/WHEEL
degiro_cli-0.1.2.dist-info/top_level.txt
degiro_cli-0.1.2.dist-info/RECORD
