Metadata-Version: 2.1
Name: degiro-cli
Version: 0.1.2
Summary: Unofficial command line tools for Degiro
Home-page: https://github.com/OhMajesticLama/degiro-cli
Author-email: ohmajesticlama@gmail.com
Project-URL: Documentation, https://ohmajesticlama.github.io/degiro-cli
Classifier: Programming Language :: Python :: 3
Classifier: License :: OSI Approved :: MIT License
Classifier: Operating System :: OS Independent
Classifier: Development Status :: 4 - Beta
Classifier: Intended Audience :: End Users/Desktop
Classifier: Topic :: Office/Business :: Financial :: Investment
Requires-Python: >=3.8
License-File: LICENSE
Requires-Dist: degiroasync (>=0.20.0)
Provides-Extra: dev
Requires-Dist: pytest (>=7.0.1) ; extra == 'dev'
Requires-Dist: coverage (>=6.3) ; extra == 'dev'
Requires-Dist: flake8 (>=4.0.1) ; extra == 'dev'
Requires-Dist: mypy (>=0.931) ; extra == 'dev'
Requires-Dist: ipython ; extra == 'dev'
Requires-Dist: ipdb ; extra == 'dev'
